<?xml version="1.0" encoding="UTF-8"?>
<!DOCTYPE suite SYSTEM "http://testng.org/testng-1.0.dtd"><suite name="All Test Suite"><test verbose="2" preserve-order="true" name="/Users/stefanstoyanov/Documents/Git/SkilloHomework/AutomationCourse/RoadToSuccess"><classes><class name="test.ChangingProfilePictureTest"><methods><include name="ChangeProfilePicture"/></methods></class><class name="test.CreatingPost"><methods><include name="UploadingPictureTest"/></methods></class><class name="test.DeletePost"><methods><include name="deletePost"/></methods></class><class name="test.LoginAndOut"><methods><include name="loginAndOut"/></methods></class><class name="test.LoginInvalidPassword"><methods><include name="LoginWithInvalidPassword"/></methods></class><class name="test.LoginInvalidUsername"><methods><include name="loginWithInvalidUsername"/></methods></class><class name="test.LoginSuccess"><methods><include name="signInWithValidCredentials"/></methods></class><class name="test.RegistrationTest"><methods><include name="successfulRegistration"/></methods></class><class name="test.ScreenshotCapture"><methods><include name="screenshotCapture"/></methods></class></classes></test></suite>